README.md
setup.py
ripple_data/__init__.py
ripple_data/accounts.py
ripple_data/currencies.py
ripple_data/exchanges.py
ripple_data/gateways.py
ripple_data/ripple_api.py
ripple_data.egg-info/PKG-INFO
ripple_data.egg-info/SOURCES.txt
ripple_data.egg-info/dependency_links.txt
ripple_data.egg-info/not-zip-safe
ripple_data.egg-info/requires.txt
ripple_data.egg-info/top_level.txt