Metadata-Version: 1.0
Name: ripple-data
Version: 0.1.2
Summary: Python API for connecting to the Ripple DATA API
Home-page: http://github.com/nl-hugo/ripple-data
Author: nl-hugo
Author-email: nl-hugo@hugojanssen.nl
License: MIT
Platform: UNKNOWN
